setup.py
gb_distributions_t.egg-info/PKG-INFO
gb_distributions_t.egg-info/SOURCES.txt
gb_distributions_t.egg-info/dependency_links.txt
gb_distributions_t.egg-info/not-zip-safe
gb_distributions_t.egg-info/top_level.txt
gb_probability_t/Binomialdistribution.py
gb_probability_t/Gaussiandistribution.py
gb_probability_t/Generaldistribution.py
gb_probability_t/__init__.py