Metadata-Version: 1.0
Name: gb-distributions-t
Version: 1.1
Summary: Gaussian and Binomial distributions
Home-page: UNKNOWN
Author: Jiahui Li
Author-email: jiahuili858@gmail.com
License: UNKNOWN
Platform: UNKNOWN
